README.md
setup.py
pyRoblox.egg-info/PKG-INFO
pyRoblox.egg-info/SOURCES.txt
pyRoblox.egg-info/dependency_links.txt
pyRoblox.egg-info/requires.txt
pyRoblox.egg-info/top_level.txt
pyroblox/__init__.py
pyroblox/client.py
pyroblox/reportManager.py
pyroblox/groups/__init__.py
pyroblox/groups/auditItem.py
pyroblox/groups/auditLog.py
pyroblox/groups/group.py
pyroblox/groups/groupConfig.py
pyroblox/groups/memberManager.py
pyroblox/groups/relationManager.py
pyroblox/groups/role.py
pyroblox/groups/socialManager.py
pyroblox/users/__init__.py
pyroblox/users/user.py