Metadata-Version: 1.1
Name: pyRoblox
Version: 0.0.3
Summary: Python library for interfacing with Roblox
Home-page: https://github.com/EchoReaper/pyroblox
Author: Drew Warwick
Author-email: dwarwick96@gmail.com
License: Apache 2.0
Platform: UNKNOWN
Classifier: Development Status :: 3 - Alpha
Classifier: Environment :: Web Environment
Classifier: Intended Audience :: Developers
Classifier: License :: OSI Approved :: Apache Software License
Classifier: Operating System :: OS Independent
Classifier: Programming Language :: Python
Classifier: Programming Language :: Python :: 3.6
